README.rst
setup.py
safeurl/__init__.py
safeurl/core.py
safeurl.egg-info/PKG-INFO
safeurl.egg-info/SOURCES.txt
safeurl.egg-info/dependency_links.txt
safeurl.egg-info/pbr.json
safeurl.egg-info/requires.txt
safeurl.egg-info/top_level.txt
tests/__init__.py
tests/tests.py