Metadata-Version: 1.0
Name: safeurl
Version: 0.0.7
Summary: Simple and clever analyzer, decoder, encoder ... urls on python, using requests
Home-page: https://github.com/FrodoTheTrue/safeurl
Author: Fedor Isakov
Author-email: mydearfrodo@yandex.ru
License: MIT
Keywords: python,analizer,urls
Platform: UNKNOWN
